MANIFEST.in
README.rst
setup.py
django_resized/__init__.py
django_resized/forms.py
django_resized/models.py
django_resized.egg-info/PKG-INFO
django_resized.egg-info/SOURCES.txt
django_resized.egg-info/dependency_links.txt
django_resized.egg-info/top_level.txt