Metadata-Version: 1.1
Name: django-resized
Version: 0.3.5
Summary: Resizes image origin to specified size.
Home-page: https://github.com/un1t/django-resized
Author: Ilya Shalyapin
Author-email: ishalyapin@gmail.com
License: MIT License
Download-URL: https://github.com/un1t/django-resized/tarball/master
Keywords: django
Platform: UNKNOWN
Classifier: Environment :: Web Environment
Classifier: Framework :: Django
Classifier: Intended Audience :: Developers
Classifier: Programming Language :: Python
Classifier: Programming Language :: Python :: 2
Classifier: Programming Language :: Python :: 2.7
Classifier: Programming Language :: Python :: 3
Classifier: Programming Language :: Python :: 3.4
Requires: python (>= 2.7)
Requires: django (>= 1.7)
